fimutil/__init__.py
fimutil/al2s/__init__.py
fimutil/al2s/al2s.conf.template
fimutil/al2s/al2s_api.py
fimutil/al2s/arm.py
fimutil/al2s/cloud_cfg.py
fimutil/netam/__init__.py
fimutil/netam/arm.py
fimutil/netam/nso.py
fimutil/netam/sr_pce.py
fimutil/ralph/__init__.py
fimutil/ralph/asset.py
fimutil/ralph/dp_switch.py
fimutil/ralph/ethernetport.py
fimutil/ralph/fim_helper.py
fimutil/ralph/fpga.py
fimutil/ralph/gpu.py
fimutil/ralph/model.py
fimutil/ralph/nvme.py
fimutil/ralph/p4_switch.py
fimutil/ralph/ralph_uri.py
fimutil/ralph/site.py
fimutil/ralph/storage.py
fimutil/ralph/worker_node.py
fimutil/utilities/__init__.py
fimutil/utilities/generate_instance_flavors.py
fimutil/utilities/scan_al2s.py
fimutil/utilities/scan_net.py
fimutil/utilities/scan_site.py
fimutil/utilities/scan_worker.py
fim_utils-1.9.2.dist-info/entry_points.txt
fim_utils-1.9.2.dist-info/LICENSE
fim_utils-1.9.2.dist-info/WHEEL
fim_utils-1.9.2.dist-info/METADATA
fim_utils-1.9.2.dist-info/RECORD
