Metadata-Version: 2.1
Name: fim_utils
Version: 1.9.2
Summary: This is a package of Information Model utilitied for FABRIC
Author-email: Ilya Baldin <ibaldin@renci.org>, Xi Yang <xiyang@es.net>, Hussamuddin Nasir <nasir@netlab.uky.edu>
Requires-Python: >=3.9
Classifier: License :: OSI Approved :: MIT License
Classifier: Programming Language :: Python :: 3
Classifier: Operating System :: OS Independent
Requires-Dist: fabric_fim >= 1.9.0
Requires-Dist: pyjq == 2.6.0
Requires-Dist: jsonpath_ng == 1.5.3
Requires-Dist: pytest ; extra == "test"
Requires-Dist: flit ; extra == "test"
Project-URL: Home, https://github.com/fabric-testbed/information-model-utils
Provides-Extra: test
